{
    "dset_name": "hl",
    "eval_split_name": "val",
    "debug": false,
    "data_ratio": 1.0,
    "results_root": "baselines/detr/results",
    "exp_id": "final_base_clip_clip_mq10_noalign",
    "seed": 2018,
    "device": 0,
    "num_workers": 4,
    "no_pin_memory": false,
    "lr": 0.0001,
    "lr_drop": 400,
    "wd": 0.0001,
    "n_epoch": 200,
    "max_es_cnt": 200,
    "bsz": 32,
    "eval_bsz": 100,
    "grad_clip": 0.1,
    "eval_untrained": false,
    "resume": null,
    "resume_all": false,
    "start_epoch": null,
    "max_q_l": 32,
    "max_v_l": 75,
    "clip_length": 2,
    "max_windows": 5,
    "train_path": "annotations/highlight_train.jsonl",
    "eval_path": "annotations/highlight_val.jsonl",
    "no_norm_vfeat": false,
    "no_norm_tfeat": false,
    "v_feat_dirs": [
        "features/clip_features"
    ],
    "t_feat_dir": "features/clip_text_features/",
    "v_feat_dim": 512,
    "t_feat_dim": 512,
    "ctx_mode": "video_tef",
    "no_hard_neg": false,
    "no_easy_neg": false,
    "position_embedding": "sine",
    "enc_layers": 2,
    "dec_layers": 2,
    "dim_feedforward": 1024,
    "hidden_dim": 256,
    "input_dropout": 0.5,
    "dropout": 0.1,
    "txt_drop_ratio": 0,
    "use_txt_pos": false,
    "nheads": 8,
    "num_queries": 10,
    "pre_norm": false,
    "n_input_proj": 2,
    "contrastive_hdim": 64,
    "temperature": 0.07,
    "lw_saliency": 1.0,
    "saliency_margin": 0.2,
    "aux_loss": true,
    "span_loss_type": "l1",
    "contrastive_align_loss": false,
    "set_cost_span": 10,
    "set_cost_giou": 1,
    "set_cost_class": 4,
    "span_loss_coef": 10,
    "giou_loss_coef": 1,
    "label_loss_coef": 4,
    "eos_coef": 0.1,
    "contrastive_align_loss_coef": 0.02,
    "no_sort_results": false,
    "max_before_nms": 10,
    "max_after_nms": 10,
    "conf_thd": 0.0,
    "nms_thd": -1.0,
    "results_dir": "moment_detr/tmp/clip_only_non_pt/"
}
